getgist/__init__.py
getgist/__main__.py
getgist/github.py
getgist/local.py
getgist/request.py
getgist-0.2.2.dist-info/entry_points.txt
getgist-0.2.2.dist-info/LICENSE
getgist-0.2.2.dist-info/WHEEL
getgist-0.2.2.dist-info/METADATA
getgist-0.2.2.dist-info/RECORD
