Metadata-Version: 2.1
Name: getgist
Version: 0.2.2
Summary: CLI to update local and remote files from GitHub Gists.
Home-page: http://github.com/cuducos/getgist
License: MIT
Keywords: gist,cli,github
Author: Eduardo Cuducos
Author-email: cuducos@users.noreply.github.com
Requires-Python: >=3.6,<4.0
Classifier: Development Status :: 4 - Beta
Classifier: Intended Audience :: Developers
Classifier: License :: OSI Approved :: MIT License
Classifier: Programming Language :: Python :: 3
Classifier: Programming Language :: Python :: 3.6
Classifier: Programming Language :: Python :: 3.7
Classifier: Programming Language :: Python :: 3.8
Classifier: Programming Language :: Python :: 3.9
Classifier: Topic :: Utilities
Requires-Dist: click (>=6.6)
Requires-Dist: requests (>=2.18.1)
Requires-Dist: tabulate (>=0.8.7)
Project-URL: Repository, http://github.com/cuducos/getgist
